napari_tifffile_reader/__init__.py
napari_tifffile_reader/_version.py
napari_tifffile_reader/napari_tifffile_reader.py
napari_tifffile_reader/_tests/__init__.py
napari_tifffile_reader/_tests/test_tifffile_reader.py
napari_tifffile_reader-0.1.1.dist-info/LICENSE
napari_tifffile_reader-0.1.1.dist-info/METADATA
napari_tifffile_reader-0.1.1.dist-info/WHEEL
napari_tifffile_reader-0.1.1.dist-info/entry_points.txt
napari_tifffile_reader-0.1.1.dist-info/top_level.txt
napari_tifffile_reader-0.1.1.dist-info/RECORD
