Metadata-Version: 2.1
Name: napari-tifffile-reader
Version: 0.1.1
Summary: A napari reader plugin for tiff images.
Home-page: https://github.com/GenevieveBuckley/napari-tifffile-reader
Author: Genevieve Buckley
License: BSD-3
Classifier: Development Status :: 4 - Beta
Classifier: Intended Audience :: Developers
Classifier: Topic :: Software Development :: Testing
Classifier: Programming Language :: Python
Classifier: Programming Language :: Python :: 3
Classifier: Programming Language :: Python :: 3.6
Classifier: Programming Language :: Python :: 3.7
Classifier: Programming Language :: Python :: 3.8
Classifier: Programming Language :: Python :: Implementation :: CPython
Classifier: Programming Language :: Python :: Implementation :: PyPy
Classifier: Operating System :: OS Independent
Classifier: License :: OSI Approved :: BSD License
Requires-Python: >=3.6
License-File: LICENSE
Requires-Dist: imagecodecs
Requires-Dist: napari-plugin-engine (>=0.1.4)
Requires-Dist: numpy
Requires-Dist: tifffile (>=2020.5.7)
Requires-Dist: vispy
